opc/__init__.py
opc/decorators.py
opc/exceptions.py
opc/lookup_table.py
py_opc-1.6.0.dist-info/METADATA
py_opc-1.6.0.dist-info/RECORD
py_opc-1.6.0.dist-info/WHEEL
py_opc-1.6.0.dist-info/top_level.txt
