Metadata-Version: 2.1
Name: py-opc
Version: 1.6.0
Summary: Python libary for operating the Alphasense OPC-N2 optical particle counter
Home-page: https://github.com/dhhagan/py-opc
Author: David H Hagan
Author-email: david@davidhhagan.com
License: MIT
Keywords: opc,alphasense,atmospheric chemistry
Platform: UNKNOWN
Classifier: Development Status :: 3 - Alpha
Classifier: Operating System :: OS Independent
Classifier: Intended Audience :: Science/Research
Classifier: Intended Audience :: Developers
Classifier: Intended Audience :: Education
Classifier: Programming Language :: Python :: 2.7
Classifier: Programming Language :: Python :: 3.3
Classifier: Programming Language :: Python :: 3.4
Classifier: Programming Language :: Python :: 3.5
Classifier: Programming Language :: Python :: 3.6
Classifier: Topic :: Scientific/Engineering :: Atmospheric Science
Classifier: Topic :: Software Development
Classifier: Topic :: System :: Hardware
